whiny/__main__.py
whiny-0.1.0.dist-info/entry_points.txt
whiny-0.1.0.dist-info/WHEEL
whiny-0.1.0.dist-info/METADATA
whiny-0.1.0.dist-info/RECORD
