Metadata-Version: 2.1
Name: whiny
Version: 0.1.0
Summary: Simple validation leveraging Python's descriptor protocol.
Home-page: https://github.com/rednafi/whiny
License: MIT
Keywords: python,validation,data,json
Author: rednafi
Author-email: redowan.nafi@gmail.com
Requires-Python: >=3.6,<4.0
Classifier: Environment :: Console
Classifier: License :: OSI Approved :: MIT License
Classifier: Operating System :: OS Independent
Classifier: Programming Language :: Python :: 3
Classifier: Programming Language :: Python :: 3.6
Classifier: Programming Language :: Python :: 3.7
Classifier: Programming Language :: Python :: 3.8
Classifier: Programming Language :: Python :: 3.9
Classifier: Topic :: Software Development
Classifier: Topic :: Software Development :: Libraries :: Python Modules
Classifier: Topic :: Software Development :: Quality Assurance
Project-URL: Repository, https://github.com/rednafi/whiny
